{"title":"模板","uid":"3c194b2f2319e046c85e1bc082983d3c","slug":"模板","date":"2022-02-16T08:35:59.408Z","updated":"2022-02-18T07:08:48.853Z","comments":true,"path":"api/articles/模板.json","keywords":null,"cover":"https://pic.imgdb.cn/item/620c7b2d2ab3f51d91aff6f7.jpg","content":"<h2 id=\"本篇文章作为跳转文章，如需阅读模板请点击下方各类按钮\"><a href=\"#本篇文章作为跳转文章，如需阅读模板请点击下方各类按钮\" class=\"headerlink\" title=\"本篇文章作为跳转文章，如需阅读模板请点击下方各类按钮\"></a>本篇文章作为跳转文章，如需阅读模板请点击下方各类按钮</h2><h3 id=\"基础算法\"><a href=\"#基础算法\" class=\"headerlink\" title=\"基础算法\"></a><a href=\"https://snailuu.github.io/post/%E5%9F%BA%E7%A1%80%E7%AE%97%E6%B3%95%E6%A8%A1%E6%9D%BF\">基础算法</a></h3><h3 id=\"数据结构\"><a href=\"#数据结构\" class=\"headerlink\" title=\"数据结构\"></a><a href=\"https://snailuu.github.io/post/%E6%95%B0%E6%8D%AE%E7%BB%93%E6%9E%84%E6%A8%A1%E6%9D%BF\">数据结构</a></h3><h3 id=\"搜索与图论\"><a href=\"#搜索与图论\" class=\"headerlink\" title=\"搜索与图论\"></a><a href=\"https://snailuu.github.io/post/%E6%90%9C%E7%B4%A2%E4%B8%8E%E5%9B%BE%E8%AE%BA%E6%A8%A1%E6%9D%BF\">搜索与图论</a></h3><h3 id=\"数学\"><a href=\"#数学\" class=\"headerlink\" title=\"数学\"></a><a href=\"https://snailuu.github.io/post/%E6%95%B0%E5%AD%A6%E6%A8%A1%E6%9D%BF\">数学</a></h3>","feature":true,"text":"本篇文章作为跳转文章，如需阅读模板请点击下方各类按钮基础算法数据结构搜索与图论数学","link":"","photos":[],"count_time":{"symbolsCount":41,"symbolsTime":"1 mins."},"categories":[{"name":"模板","slug":"模板","count":5,"path":"api/categories/模板.json"}],"tags":[],"toc":"<ol class=\"toc\"><li class=\"toc-item toc-level-2\"><a class=\"toc-link\" href=\"#%E6%9C%AC%E7%AF%87%E6%96%87%E7%AB%A0%E4%BD%9C%E4%B8%BA%E8%B7%B3%E8%BD%AC%E6%96%87%E7%AB%A0%EF%BC%8C%E5%A6%82%E9%9C%80%E9%98%85%E8%AF%BB%E6%A8%A1%E6%9D%BF%E8%AF%B7%E7%82%B9%E5%87%BB%E4%B8%8B%E6%96%B9%E5%90%84%E7%B1%BB%E6%8C%89%E9%92%AE\"><span class=\"toc-text\">本篇文章作为跳转文章，如需阅读模板请点击下方各类按钮</span></a><ol class=\"toc-child\"><li class=\"toc-item toc-level-3\"><a class=\"toc-link\" href=\"#%E5%9F%BA%E7%A1%80%E7%AE%97%E6%B3%95\"><span class=\"toc-text\">基础算法</span></a></li><li class=\"toc-item toc-level-3\"><a class=\"toc-link\" href=\"#%E6%95%B0%E6%8D%AE%E7%BB%93%E6%9E%84\"><span class=\"toc-text\">数据结构</span></a></li><li class=\"toc-item toc-level-3\"><a class=\"toc-link\" href=\"#%E6%90%9C%E7%B4%A2%E4%B8%8E%E5%9B%BE%E8%AE%BA\"><span class=\"toc-text\">搜索与图论</span></a></li><li class=\"toc-item toc-level-3\"><a class=\"toc-link\" href=\"#%E6%95%B0%E5%AD%A6\"><span class=\"toc-text\">数学</span></a></li></ol></li></ol>","author":{"name":"Snailuu","slug":"blog-author","avatar":"https://s3.bmp.ovh/imgs/2022/02/cf596ea7a7a4830f.jpg","link":"/","description":"本就无一物，何惧世道无常","socials":{"github":"https://github.com/snailuu","twitter":"","stackoverflow":"","wechat":"","qq":"","weibo":"","zhihu":"","csdn":"","juejin":"","customs":{}}},"mapped":true,"prev_post":{},"next_post":{"title":"杂乱笔记","uid":"40516069856649c61c80ebcc0b14851f","slug":"杂点笔记","date":"2022-02-16T04:06:58.194Z","updated":"2022-02-27T00:51:50.931Z","comments":true,"path":"api/articles/杂点笔记.json","keywords":null,"cover":"https://pic.imgdb.cn/item/620c7af22ab3f51d91afbaa6.jpg","text":"字符串 string类的插入insert(pos,string) 在下标pos和pos+1之间插入字符串string。 string类的删除earse(pos,num)从下标pos开始删除num个字符，如果num为空则删除pos后面的所有字符。 数学 取模的顺序：一定要优先对可能...","link":"","photos":[],"count_time":{"symbolsCount":527,"symbolsTime":"1 mins."},"categories":[{"name":"笔记","slug":"笔记","count":1,"path":"api/categories/笔记.json"}],"tags":[{"name":"数学","slug":"数学","count":2,"path":"api/tags/数学.json"},{"name":"字符串","slug":"字符串","count":1,"path":"api/tags/字符串.json"},{"name":"动态规划","slug":"动态规划","count":2,"path":"api/tags/动态规划.json"}],"author":{"name":"Snailuu","slug":"blog-author","avatar":"https://s3.bmp.ovh/imgs/2022/02/cf596ea7a7a4830f.jpg","link":"/","description":"本就无一物，何惧世道无常","socials":{"github":"https://github.com/snailuu","twitter":"","stackoverflow":"","wechat":"","qq":"","weibo":"","zhihu":"","csdn":"","juejin":"","customs":{}}},"feature":true}}