{"title":"Snailuu's Blog","subtitle":"","description":"本就无一物，何惧世道无常","author":"Snailuu","language":"zh-CN","timezone":"","url":"https://snailuu.github.io","root":"/","permalink":"/post/:title.html","permalink_defaults":null,"pretty_urls":{"trailing_index":true,"trailing_html":true},"source_dir":"source","public_dir":"public","tag_dir":"tags","archive_dir":"archives","category_dir":"categories","code_dir":"downloads/code","i18n_dir":":lang","skip_render":null,"new_post_name":":title.md","default_layout":"post","titlecase":false,"external_link":{"enable":true,"field":"site","exclude":""},"filename_case":0,"render_drafts":false,"post_asset_folder":false,"relative_link":false,"future":true,"highlight":{"enable":false,"auto_detect":false,"line_number":true,"tab_replace":"","wrap":true,"hljs":false},"prismjs":{"enable":true,"preprocess":true,"line_number":true,"tab_replace":""},"default_category":"uncategorized","category_map":null,"tag_map":null,"date_format":"YYYY-MM-DD","time_format":"HH:mm:ss","updated_option":"mtime","per_page":18,"pagination_dir":"page","theme":"aurora","server":{"port":4000,"log":false,"compress":false,"header":true,"cache":false},"deploy":{"type":"git","repository":"https://github.com/snailuu/snailuu.github.io.git","branch":"main"},"ignore":null,"meta_generator":true,"keywords":null,"index_generator":{"per_page":18,"order_by":"-date","path":""},"include":null,"exclude":null,"mathjax":{"tags":"none","single_dollars":true,"cjk_width":0.9,"normal_width":0.6,"append_css":true,"every_page":false,"extension_options":{}},"theme_config":{"site":{"subtitle":"Snailuu's Blog","author":"Snailuu","nick":"人生无常，大肠包小肠","description":"本就无一物，何惧世道无常","link":"/","language":"cn","multi_language":true,"logo":"https://pic.imgdb.cn/item/62035c342ab3f51d91f6154a.jpg","avatar":"https://pic.imgdb.cn/item/62035c342ab3f51d91f6154a.jpg","beian":{"number":"","link":""},"police_beian":{"number":"","link":""}},"authors":null,"menu":{"About":true,"Tags":true,"Archives":true,"contact":{"name":"GitHub","i18n":{"cn":"联系我","en":"Contact"},"path":"https://github.com/snailuu"}},"theme":{"dark_mode":true,"profile_shape":"rounded","feature":true,"gradient":{"color_1":"#30cfd0","color_2":"#1f618d","color_3":"#330867"}},"socials":{"customs":null,"github":"https://github.com/snailuu"},"site_meta":{"cdn":"cn","favicon":null,"description":"","keywords":"","author":""},"gitalk":{"enable":false,"autoExpand":true,"clientID":"","clientSecret":"","repo":"dev-blog-comments","owner":"TriDiamond","admin":["TriDiamond"],"id":"uid","language":"en","distractionFreeMode":true,"recentComment":false,"proxy":""},"valine":{"enable":false,"app_id":null,"app_key":null,"avatar":"","placeholder":"Leave your thoughts behind~","visitor":true,"lang":"en","avatarForce":false,"meta":["nick","mail"],"requiredFields":[],"admin":"TriDiamond","recentComment":false},"busuanzi":{"enable":true},"copy_protection":{"enable":false,"author":{"cn":"snailuu","en":"Snialuu"},"link":{"cn":"本文来自于https://snailuu.github.io/","en":"Article is fromhttps://snailuu.github.io/"},"license":{"cn":null,"en":null}},"aurora_bot":{"enable":false,"locale":"en","bot_type":"dia","tips":null},"injects":{"scripts":null,"css":null},"version":"1.5.5"},"archive_generator":{"per_page":18,"yearly":true,"monthly":true,"daily":false},"tag_generator":{"per_page":18},"category_generator":{"per_page":18},"marked":{"gfm":true,"pedantic":false,"breaks":true,"smartLists":true,"smartypants":true,"modifyAnchors":0,"autolink":true,"mangle":true,"sanitizeUrl":false,"dompurify":false,"headerIds":true,"anchorAlias":false,"lazyload":false,"prependRoot":true,"postAsset":false,"external_link":{"enable":false,"exclude":[],"nofollow":false},"descriptionLists":true}}